autotest/__init__.py
autotest/xml/__init__.py
autotest/xml/xmlCheck.py
smartfeedads/__init__.py
smartfeedads/eventtrace/__init__.py
smartfeedads/eventtrace/eventtraceCheck.py
smartfeedads/xml/__init__.py
smartfeedads/xml/xmlCheck.py
smartfeed_ads-1.0.5.dist-info/METADATA
smartfeed_ads-1.0.5.dist-info/WHEEL
smartfeed_ads-1.0.5.dist-info/top_level.txt
smartfeed_ads-1.0.5.dist-info/RECORD
