Metadata-Version: 2.1
Name: smartfeed_ads
Version: 1.0.5
Summary: 用于smartfeed和流量渠道自动化测试工具包
Home-page: UNKNOWN
Author: zhouyanhui
License: UNKNOWN
Platform: UNKNOWN
